{
  "$id": "https://gcn.nasa.gov/schema/main/gcn/notices/dsa110/frb.schema.json",
  "$schema": "https://json-schema.org/draft/2020-12/schema",
  "title": "DSA-110 FRB Alert",
  "description": "Fast radio burst alert from the Deep Synoptic Array 110.",
  "type": "object",
  "allOf": [
    { "$ref": "../core/Alert.schema.json" },
    { "$ref": "../core/Reporter.schema.json" },
    { "$ref": "../core/Event.schema.json" },
    { "$ref": "../core/DateTime.schema.json" },
    { "$ref": "../core/Localization.schema.json" },
    { "$ref": "../core/DispersionMeasure.schema.json" }
  ],
  "properties": {
    "$schema": {
      "type": "string",
      "format": "uri"
    },
    "importance": {
      "type": "number",
      "description": "A machine learning score separating RFI (0) from an astrophysical signal (1)"
    },
    "event_duration": {
      "type": "number",
      "description": "Time duration of the event in milliseconds"
    },
    "snr": {
      "type": "number",
      "description": "Signal to noise ratio of burst [dimensionless]"
    },
    "description": {
      "type": "string",
      "description": "Description of how the event was identified and what it represents."
    },
    "known_source": {
      "type": "string",
      "description": "Name of a known FRB that this event has been associated to."
    }
  },
  "unevaluatedProperties": false
}
